pyszn/__init__.py
pyszn/injection.py
pyszn/parser.py
pyszn-1.7.0.dist-info/LICENSE
pyszn-1.7.0.dist-info/METADATA
pyszn-1.7.0.dist-info/WHEEL
pyszn-1.7.0.dist-info/top_level.txt
pyszn-1.7.0.dist-info/RECORD
