Metadata-Version: 2.1
Name: pyszn
Version: 1.7.0
Summary: A Python package for the Simplified Zone Notation standard
Home-page: https://pyszn.readthedocs.org/
Author: Hewlett Packard Enterprise Development LP
Author-email: hpe-networking@lists.hp.com
Keywords: pyszn
Classifier: Development Status :: 3 - Alpha
Classifier: Intended Audience :: Developers
Classifier: License :: OSI Approved :: Apache Software License
Classifier: Natural Language :: English
Classifier: Operating System :: POSIX :: Linux
Classifier: Programming Language :: Python :: 3
Classifier: Programming Language :: Python :: 3.5
License-File: LICENSE
Requires-Dist: pyparsing
